my_serializer/constants.py
my_serializer/serializer.py
my_serializer/serializer_fabric.py
my_serializer/serializer_json.py
my_serializer/serializer_xml.py
serializerLiza153501/constants.py
serializerLiza153501/serializer.py
serializerLiza153501/serializer_fabric.py
serializerLiza153501/serializer_json.py
serializerLiza153501/serializer_xml.py
serializerLiza153501-0.1.2.dist-info/METADATA
serializerLiza153501-0.1.2.dist-info/WHEEL
serializerLiza153501-0.1.2.dist-info/top_level.txt
serializerLiza153501-0.1.2.dist-info/RECORD
